MANIFEST.in
VERSION
requirements.txt
setup.py
docs/source/conf.py
examples/basic-async.py
examples/basic-config.py
examples/basic-dto.py
examples/basic-etc.py
examples/basic-fetch.py
examples/basic-local.py
examples/basic.py
examples/fetch.py
examples/field.py
examples/schema.py
unimatrix.ext.secrets.egg-info/PKG-INFO
unimatrix.ext.secrets.egg-info/SOURCES.txt
unimatrix.ext.secrets.egg-info/dependency_links.txt
unimatrix.ext.secrets.egg-info/entry_points.txt
unimatrix.ext.secrets.egg-info/requires.txt
unimatrix.ext.secrets.egg-info/top_level.txt
unimatrix/ext/secrets/__boot__.py
unimatrix/ext/secrets/__init__.py
unimatrix/ext/secrets/conf.py
unimatrix/ext/secrets/field.py
unimatrix/ext/secrets/package.json
unimatrix/ext/secrets/registry.py
unimatrix/ext/secrets/repository.py
unimatrix/ext/secrets/schema.py
unimatrix/ext/secrets/secret.py
unimatrix/ext/secrets/providers/__init__.py
unimatrix/ext/secrets/providers/azure.py
unimatrix/ext/secrets/providers/base.py
unimatrix/ext/secrets/providers/config.py
unimatrix/ext/secrets/providers/google.py
unimatrix/ext/secrets/providers/local.py
unimatrix/ext/secrets/providers/schema.py